jl95/net/io/__init__.py
jl95/net/io/collections.py
jl95/net/io/constants.py
jl95/net/io/util.py
jl95terceira_net_io-1.5.0.dist-info/METADATA
jl95terceira_net_io-1.5.0.dist-info/WHEEL
jl95terceira_net_io-1.5.0.dist-info/RECORD
