Metadata-Version: 2.4
Name: jl95terceira_net_io
Version: 1.5.0
Summary: Python command line tools collection (general)
Project-URL: Homepage, https://github.com/jl95terceira/net-io-python
Project-URL: Issues, https://github.com/jl95terceira/net-io-python/issues
Author-email: Joao Luis Ornelas da Silva <jl95terceira@gmail.com>
Classifier: License :: OSI Approved :: MIT License
Classifier: Operating System :: OS Independent
Classifier: Programming Language :: Python :: 3
Requires-Python: >=3.12
